shoutout/__init__.py
shoutout/broadcast.py
shoutout_py-0.1.0.dist-info/WHEEL
shoutout_py-0.1.0.dist-info/METADATA
shoutout_py-0.1.0.dist-info/RECORD
