Metadata-Version: 2.1
Name: shoutout-py
Version: 0.1.0
Summary: Realtime messaging with Redis PUB/SUB.
Home-page: https://github.com/alexvanzyl/shoutout
Keywords: websocket,redis,fastapi,pubsub,realtime
Author: Alexander van Zyl
Author-email: vanzyl.alex@gmail.com
Requires-Python: >=3.8,<4.0
Classifier: Programming Language :: Python :: 3
Classifier: Programming Language :: Python :: 3.8
Classifier: Programming Language :: Python :: 3.9
Requires-Dist: aioredis (>=1.3.1,<2.0.0)
Project-URL: Repository, https://github.com/alexvanzyl/shoutout
